stocksymbol/__init__.py
stocksymbol/symbols.py
stocksymbol-0.0.5.dist-info/LICENSE
stocksymbol-0.0.5.dist-info/METADATA
stocksymbol-0.0.5.dist-info/WHEEL
stocksymbol-0.0.5.dist-info/top_level.txt
stocksymbol-0.0.5.dist-info/RECORD
