Metadata-Version: 2.1
Name: stocksymbol
Version: 0.0.5
Summary: Provides a list of stock symbols from all major stock exchanges across various regions and markets.
Home-page: https://github.com/yongghongg/stock-symbol
Author: Yonghong Tan
Author-email: yongghongg@hotmail.com
License: UNKNOWN
Platform: UNKNOWN
Classifier: Programming Language :: Python :: 3
Classifier: License :: OSI Approved :: MIT License
Classifier: Operating System :: OS Independent
Requires-Python: >=3.7
License-File: LICENSE
